ImageDimensionCheck/__init__.py
ImageDimensionCheck-1.4.2.dist-info/License.txt
ImageDimensionCheck-1.4.2.dist-info/METADATA
ImageDimensionCheck-1.4.2.dist-info/WHEEL
ImageDimensionCheck-1.4.2.dist-info/top_level.txt
ImageDimensionCheck-1.4.2.dist-info/RECORD
